Metadata-Version: 2.1
Name: pysaur
Version: 0.4
Summary: pysaur module
Home-page: UNKNOWN
Author-email: oleksiy.saurin@gmail.com
License: UNKNOWN
Platform: UNKNOWN
